diga_olar/__init__.py
diga_olar/funcoes.py
diga_olar-0.0.1.dist-info/METADATA
diga_olar-0.0.1.dist-info/WHEEL
diga_olar-0.0.1.dist-info/top_level.txt
diga_olar-0.0.1.dist-info/RECORD
