Metadata-Version: 2.1
Name: diga-olar
Version: 0.0.1
Summary: Diga olá da forma mais estilosa na língua brasileira
Home-page: https://github.com/girol/diga-olar
Author: André Girol
Author-email: andregirol@gmail.com
License: UNKNOWN
Platform: UNKNOWN
Classifier: Programming Language :: Python :: 3
Classifier: License :: OSI Approved :: MIT License
Classifier: Operating System :: OS Independent
